Metadata-Version: 2.1
Name: elon
Version: 0.2.2
Summary: Lightweight async job queue backed by redis.
Home-page: http://github.com/omarish/elon
Author: Omar Bohsali
Author-email: omar.bohsali@gmail.com
License: MIT
Platform: UNKNOWN
